printDebugging/__init__.py
printDebugging/debugger.py
print_debugging-0.0.2.dist-info/LICENSE
print_debugging-0.0.2.dist-info/METADATA
print_debugging-0.0.2.dist-info/WHEEL
print_debugging-0.0.2.dist-info/top_level.txt
print_debugging-0.0.2.dist-info/RECORD
