Metadata-Version: 2.1
Name: print-debugging
Version: 0.0.2
Summary: Load module, function from string
Home-page: https://github.com/benjamin-jin/debugger
Author: Benjamin Jin
Author-email: jinrudals135@naver.com
License: UNKNOWN
Platform: UNKNOWN
License-File: LICENSE
Requires-Dist: ansicolors
Requires-Dist: dynamic-load
